setup.py
cameo_fastapi/__init__.py
cameo_fastapi/__main__.py
cameo_fastapi/cameo_fastapi.py
cameo_fastapi.egg-info/PKG-INFO
cameo_fastapi.egg-info/SOURCES.txt
cameo_fastapi.egg-info/dependency_links.txt
cameo_fastapi.egg-info/requires.txt
cameo_fastapi.egg-info/top_level.txt