Metadata-Version: 2.1
Name: cameo-fastapi
Version: 0.2.6
Summary: CAMEO FastAPI2022-04-01 v0.2.6 init_fastapi() to init()
Home-page: https://github.com/bohachu/cameo_fastapi
Author: Bowen Chiu
Author-email: bohachu@gmail.com
License: BSD 0-clause license
Platform: UNKNOWN
Classifier: Programming Language :: Python :: 3
